kmsfsw/__init__.py
kmsfsw/__main__.py
kmsfsw/main.py
kxmcmcpfilesystemwin-0.1.9.dist-info/METADATA
kxmcmcpfilesystemwin-0.1.9.dist-info/WHEEL
kxmcmcpfilesystemwin-0.1.9.dist-info/entry_points.txt
kxmcmcpfilesystemwin-0.1.9.dist-info/top_level.txt
kxmcmcpfilesystemwin-0.1.9.dist-info/RECORD
