Metadata-Version: 2.4
Name: KxmcMcpFileSystemWin
Version: 0.1.9
Summary: 操作windows文件和目录
Requires-Python: >=3.13
Requires-Dist: mcp>=1.6.0
Requires-Dist: setuptools>=79.0.1
